[
  {
    "company": "wakayama",
    "companyName": "和歌山バス",
    "vehicleNum": "1976",
    "lat": 34.27138900756836,
    "lon": 135.14859008789062,
    "route": "和歌山大学線【172】（ＪＲ和歌山駅行き）",
    "stop": "西三番丁",
    "tripId": "106_609_20260404",
    "bearing": 0,
    "speed": 4.722222328186035,
    "updateTime": "2026/07/22 21:17:13"
  },
  {
    "company": "wakayama",
    "companyName": "和歌山バス",
    "vehicleNum": "321",
    "lat": 34.20277786254883,
    "lon": 135.17050170898438,
    "route": "和歌山市内線【13】（和歌浦西行き）",
    "stop": "水軒口",
    "tripId": "106_479_20260404",
    "bearing": 0,
    "speed": 0.2777777910232544,
    "updateTime": "2026/07/22 21:17:43"
  },
  {
    "company": "wakayama",
    "companyName": "和歌山バス",
    "vehicleNum": "367",
    "lat": 34.23158264160156,
    "lon": 135.1846923828125,
    "route": "和歌山市内線【20】（ＪＲ和歌山駅行き）",
    "stop": "新内",
    "tripId": "106_571_20260404",
    "bearing": 0,
    "speed": 5,
    "updateTime": "2026/07/22 21:17:23"
  },
  {
    "company": "wakayama",
    "companyName": "和歌山バス",
    "vehicleNum": "373",
    "lat": 34.23358154296875,
    "lon": 135.16949462890625,
    "route": "和歌山市内線【13】（南海和歌山市駅行き）",
    "stop": "城北橋",
    "tripId": "106_557_20260404",
    "bearing": 0,
    "speed": 0,
    "updateTime": "2026/07/22 21:17:39"
  },
  {
    "company": "wakayama",
    "companyName": "和歌山バス",
    "vehicleNum": "454",
    "lat": 34.188777923583984,
    "lon": 135.17538452148438,
    "route": "和歌山市内線【20】（ＪＲ和歌山駅行き）",
    "stop": "津屋",
    "tripId": "106_970_20260404",
    "bearing": 0,
    "speed": 6.388888835906982,
    "updateTime": "2026/07/22 21:17:07"
  },
  {
    "company": "wakayama-naga",
    "companyName": "和歌山バス那賀",
    "vehicleNum": "497",
    "lat": 34.323001861572266,
    "lon": 135.37689208984375,
    "route": "粉河熊取線【急】（粉河駅前行き）",
    "stop": "神通",
    "tripId": "2_45_2502_1_179_20260401",
    "bearing": 0,
    "speed": 5.833333492279053,
    "updateTime": "2026/07/22 21:16:36"
  },
  {
    "company": "wakayama",
    "companyName": "和歌山バス",
    "vehicleNum": "534",
    "lat": 34.25299835205078,
    "lon": 135.14639282226562,
    "route": "坂田線【75】",
    "stop": "延時",
    "tripId": "106_961_20260404",
    "bearing": 0,
    "speed": 6.388888835906982,
    "updateTime": "2026/07/22 21:17:45"
  },
  {
    "company": "wakayama-naga",
    "companyName": "和歌山バス那賀",
    "vehicleNum": "583",
    "lat": 34.3118896484375,
    "lon": 135.30728149414062,
    "route": "岩出樽井線【201,202】（樽井駅前行き）",
    "stop": "根来さくらの里",
    "tripId": "2_45_2601_1_224_20260401",
    "bearing": 0,
    "speed": 0.5555555820465088,
    "updateTime": "2026/07/22 21:17:25"
  },
  {
    "company": "wakayama-naga",
    "companyName": "和歌山バス那賀",
    "vehicleNum": "643",
    "lat": 34.268890380859375,
    "lon": 135.24668884277344,
    "route": "紀伊粉河線【24】（粉河駅前行き）",
    "stop": "紀伊駅前",
    "tripId": "2_45_2241_1_144_20260401",
    "bearing": 0,
    "speed": 0,
    "updateTime": "2026/07/22 21:16:53"
  },
  {
    "company": "wakayama-naga",
    "companyName": "和歌山バス那賀",
    "vehicleNum": "737",
    "lat": 34.277889251708984,
    "lon": 135.29818725585938,
    "route": "紀伊粉河線【26】（近畿大学行き）",
    "stop": "安上",
    "tripId": "2_45_2261_1_169_20260401",
    "bearing": 0,
    "speed": 2.5,
    "updateTime": "2026/07/22 21:17:20"
  },
  {
    "company": "wakayama-naga",
    "companyName": "和歌山バス那賀",
    "vehicleNum": "760",
    "lat": 34.34700012207031,
    "lon": 135.28488159179688,
    "route": "岩出樽井線【201,202】（岩出駅前行き）",
    "stop": "砂川駅前",
    "tripId": "2_45_2602_1_156_20260401",
    "bearing": 0,
    "speed": 5.833333492279053,
    "updateTime": "2026/07/22 21:17:14"
  },
  {
    "company": "wakayama",
    "companyName": "和歌山バス",
    "vehicleNum": "770",
    "lat": 34.15877914428711,
    "lon": 135.20150756835938,
    "route": "和歌山市内線【6】（和歌浦西行き）",
    "stop": "黒江",
    "tripId": "106_498_20260404",
    "bearing": 0,
    "speed": 6.388888835906982,
    "updateTime": "2026/07/22 21:17:25"
  },
  {
    "company": "wakayama",
    "companyName": "和歌山バス",
    "vehicleNum": "781",
    "lat": 34.25758361816406,
    "lon": 135.14427185058594,
    "route": "和歌山大学線【172】（東二番丁北行き）",
    "stop": "向団地",
    "tripId": "106_689_20260404",
    "bearing": 0,
    "speed": 4.166666507720947,
    "updateTime": "2026/07/22 21:17:15"
  },
  {
    "company": "wakayama",
    "companyName": "和歌山バス",
    "vehicleNum": "791",
    "lat": 34.21977615356445,
    "lon": 135.1693878173828,
    "route": "和歌山市内線【25】（和歌浦西行き）",
    "stop": "日赤医療センター前",
    "tripId": "106_663_20260404",
    "bearing": 0,
    "speed": 1.3888888359069824,
    "updateTime": "2026/07/22 21:17:10"
  },
  {
    "company": "wakayama",
    "companyName": "和歌山バス",
    "vehicleNum": "833",
    "lat": 34.22627639770508,
    "lon": 135.1750030517578,
    "route": "湊線【161】（和歌山港駅行き）",
    "stop": "岡山町",
    "tripId": "106_951_20260404",
    "bearing": 0,
    "speed": 3.8888888359069824,
    "updateTime": "2026/07/22 21:17:00"
  },
  {
    "company": "wakayama",
    "companyName": "和歌山バス",
    "vehicleNum": "951",
    "lat": 34.16658401489258,
    "lon": 135.18739318847656,
    "route": "和歌山市内線【17】（海南駅前行き）",
    "stop": "競技場前",
    "tripId": "106_595_20260404",
    "bearing": 0,
    "speed": 6.666666507720947,
    "updateTime": "2026/07/22 21:17:37"
  }
]
