[
  {
    "company": "wakayama",
    "companyName": "和歌山バス",
    "vehicleNum": "1960",
    "lat": 34.213584899902344,
    "lon": 135.17039489746094,
    "route": "和歌山市内線【121】（ＪＲ和歌山駅行き）",
    "stop": "堀止",
    "tripId": "109_6093_20260404",
    "bearing": 0,
    "speed": 0,
    "updateTime": "2026/07/20 20:47:30"
  },
  {
    "company": "wakayama",
    "companyName": "和歌山バス",
    "vehicleNum": "1976",
    "lat": 34.26499938964844,
    "lon": 135.14988708496094,
    "route": "和歌山大学線【172】（東二番丁北行き）",
    "stop": "和歌山大学",
    "tripId": "109_6107_20260404",
    "bearing": 0,
    "speed": 1.9444444179534912,
    "updateTime": "2026/07/20 20:47:33"
  },
  {
    "company": "wakayama",
    "companyName": "和歌山バス",
    "vehicleNum": "367",
    "lat": 34.20500183105469,
    "lon": 135.17088317871094,
    "route": "和歌山市内線【25】（和歌浦西行き）",
    "stop": "水軒口",
    "tripId": "109_5931_20260404",
    "bearing": 0,
    "speed": 5.833333492279053,
    "updateTime": "2026/07/20 20:47:36"
  },
  {
    "company": "wakayama",
    "companyName": "和歌山バス",
    "vehicleNum": "373",
    "lat": 34.23208236694336,
    "lon": 135.1898956298828,
    "route": "紀三井寺線【44】（医大病院行き）",
    "stop": "ＪＲ和歌山駅",
    "tripId": "109_5978_20260404",
    "bearing": 0,
    "speed": 2.222222328186035,
    "updateTime": "2026/07/20 20:47:03"
  },
  {
    "company": "wakayama",
    "companyName": "和歌山バス",
    "vehicleNum": "454",
    "lat": 34.25788879394531,
    "lon": 135.17489624023438,
    "route": "楠見線【88】（ＪＲ和歌山駅行き）",
    "stop": "楠見小学校前",
    "tripId": "109_6256_20260404",
    "bearing": 0,
    "speed": 6.111111164093018,
    "updateTime": "2026/07/20 20:47:39"
  },
  {
    "company": "wakayama",
    "companyName": "和歌山バス",
    "vehicleNum": "457",
    "lat": 34.23127746582031,
    "lon": 135.18238830566406,
    "route": "和歌山大学線【172】（ＪＲ和歌山駅行き）",
    "stop": "北の新地",
    "tripId": "109_6242_20260404",
    "bearing": 0,
    "speed": 4.166666507720947,
    "updateTime": "2026/07/20 20:47:11"
  },
  {
    "company": "wakayama",
    "companyName": "和歌山バス",
    "vehicleNum": "772",
    "lat": 34.22658157348633,
    "lon": 135.16949462890625,
    "route": "和歌山市内線【13】（南海和歌山市駅行き）",
    "stop": "県庁前",
    "tripId": "109_6080_20260404",
    "bearing": 0,
    "speed": 0,
    "updateTime": "2026/07/20 20:47:44"
  },
  {
    "company": "wakayama",
    "companyName": "和歌山バス",
    "vehicleNum": "781",
    "lat": 34.1879997253418,
    "lon": 135.16207885742188,
    "route": "西浜新和歌浦線【35】",
    "stop": "新和歌浦",
    "tripId": "109_5944_20260404",
    "bearing": 0,
    "speed": 1.1111111640930176,
    "updateTime": "2026/07/20 20:47:29"
  },
  {
    "company": "wakayama",
    "companyName": "和歌山バス",
    "vehicleNum": "789",
    "lat": 34.27338790893555,
    "lon": 135.14889526367188,
    "route": "和歌山大学線【172】（ＪＲ和歌山駅行き）",
    "stop": "西四番丁",
    "tripId": "109_6053_20260404",
    "bearing": 0,
    "speed": 0,
    "updateTime": "2026/07/20 20:47:07"
  },
  {
    "company": "wakayama",
    "companyName": "和歌山バス",
    "vehicleNum": "791",
    "lat": 34.22997283935547,
    "lon": 135.18028259277344,
    "route": "和歌山市内線【25】（和歌浦西行き）",
    "stop": "三木町新通",
    "tripId": "109_5961_20260404",
    "bearing": 0,
    "speed": 4.722222328186035,
    "updateTime": "2026/07/20 20:45:32"
  },
  {
    "company": "wakayama",
    "companyName": "和歌山バス",
    "vehicleNum": "799",
    "lat": 34.259193420410156,
    "lon": 135.18777465820312,
    "route": "楠見線【88】（南海和歌山市駅行き）",
    "stop": "善明寺",
    "tripId": "109_6068_20260404",
    "bearing": 0,
    "speed": 5,
    "updateTime": "2026/07/20 20:47:17"
  },
  {
    "company": "wakayama-naga",
    "companyName": "和歌山バス那賀",
    "vehicleNum": "800",
    "lat": 34.28419494628906,
    "lon": 135.29100036621094,
    "route": "紀伊粉河線【24】（粉河駅前行き）",
    "stop": "紀泉台北",
    "tripId": "2_46_2241_1_469_20260401",
    "bearing": 0,
    "speed": 2.777777671813965,
    "updateTime": "2026/07/20 20:47:21"
  },
  {
    "company": "wakayama",
    "companyName": "和歌山バス",
    "vehicleNum": "816",
    "lat": 34.237083435058594,
    "lon": 135.1743927001953,
    "route": "紀三井寺線【42】（南海和歌山市駅行き）",
    "stop": "本町四丁目",
    "tripId": "109_6230_20260404",
    "bearing": 0,
    "speed": 0,
    "updateTime": "2026/07/20 20:47:41"
  },
  {
    "company": "wakayama",
    "companyName": "和歌山バス",
    "vehicleNum": "832",
    "lat": 34.18869400024414,
    "lon": 135.18557739257812,
    "route": "紀三井寺線【42】（南海和歌山市駅行き）",
    "stop": "医大病院東口",
    "tripId": "109_6277_20260404",
    "bearing": 0,
    "speed": 6.388888835906982,
    "updateTime": "2026/07/20 20:47:30"
  },
  {
    "company": "wakayama",
    "companyName": "和歌山バス",
    "vehicleNum": "864",
    "lat": 34.1619987487793,
    "lon": 135.18807983398438,
    "route": "和歌山市内線【117】（南海和歌山市駅行き）",
    "stop": "浜の宮",
    "tripId": "109_6039_20260404",
    "bearing": 0,
    "speed": 5.833333492279053,
    "updateTime": "2026/07/20 20:47:23"
  },
  {
    "company": "wakayama-naga",
    "companyName": "和歌山バス那賀",
    "vehicleNum": "908",
    "lat": 34.273193359375,
    "lon": 135.27499389648438,
    "route": "紀伊粉河線【25】（Ｆ．Ｂ．Ｔ（和歌山バス那賀）行き）",
    "stop": "山村西",
    "tripId": "2_46_2252_1_490_20260401",
    "bearing": 0,
    "speed": 6.111111164093018,
    "updateTime": "2026/07/20 20:47:33"
  },
  {
    "company": "wakayama-naga",
    "companyName": "和歌山バス那賀",
    "vehicleNum": "962",
    "lat": 34.26288986206055,
    "lon": 135.31219482421875,
    "route": "岩出りんくう線【203】（岩出駅前行き）",
    "stop": "中迫",
    "tripId": "2_46_2632_1_455_20260401",
    "bearing": 0,
    "speed": 4.722222328186035,
    "updateTime": "2026/07/20 20:47:17"
  },
  {
    "company": "wakayama",
    "companyName": "和歌山バス",
    "vehicleNum": "978",
    "lat": 34.16608428955078,
    "lon": 135.18739318847656,
    "route": "和歌山市内線【20】（海南駅前行き）",
    "stop": "競技場前",
    "tripId": "109_6024_20260404",
    "bearing": 0,
    "speed": 5.833333492279053,
    "updateTime": "2026/07/20 20:47:40"
  }
]
