[
  {
    "company": "wakayama",
    "companyName": "和歌山バス",
    "vehicleNum": "115",
    "lat": 34.22997283935547,
    "lon": 135.17578125,
    "route": "和歌山大学線【172】（ＪＲ和歌山駅行き）",
    "stop": "和歌山城前",
    "tripId": "106_877_20260404",
    "bearing": 0,
    "speed": 1.1111111640930176,
    "updateTime": "2026/07/21 19:19:13"
  },
  {
    "company": "wakayama",
    "companyName": "和歌山バス",
    "vehicleNum": "1960",
    "lat": 34.18869400024414,
    "lon": 135.17608642578125,
    "route": "和歌山市内線【117】（海南駅前行き）",
    "stop": "津屋",
    "tripId": "106_672_20260404",
    "bearing": 0,
    "speed": 3.3333332538604736,
    "updateTime": "2026/07/21 19:19:24"
  },
  {
    "company": "wakayama",
    "companyName": "和歌山バス",
    "vehicleNum": "1976",
    "lat": 34.231388092041016,
    "lon": 135.1842803955078,
    "route": "和歌山市内線【121】（海南駅前行き）",
    "stop": "北の新地",
    "tripId": "106_569_20260404",
    "bearing": 0,
    "speed": 3.6111111640930176,
    "updateTime": "2026/07/21 19:19:38"
  },
  {
    "company": "wakayama",
    "companyName": "和歌山バス",
    "vehicleNum": "231",
    "lat": 34.190887451171875,
    "lon": 135.14669799804688,
    "route": "市内雑賀崎循環線【34】（養翠園前行き）",
    "stop": "雑賀崎",
    "tripId": "106_843_20260404",
    "bearing": 0,
    "speed": 3.055555582046509,
    "updateTime": "2026/07/21 19:19:39"
  },
  {
    "company": "wakayama",
    "companyName": "和歌山バス",
    "vehicleNum": "232",
    "lat": 34.26769256591797,
    "lon": 135.18569946289062,
    "route": "楠見線【86】（鳴滝団地行き）",
    "stop": "近畿大学附属和歌山校前",
    "tripId": "106_893_20260404",
    "bearing": 0,
    "speed": 3.6111111640930176,
    "updateTime": "2026/07/21 19:19:37"
  },
  {
    "company": "wakayama",
    "companyName": "和歌山バス",
    "vehicleNum": "259",
    "lat": 34.207000732421875,
    "lon": 135.17149353027344,
    "route": "和歌山市内線【25】（和歌浦西行き）",
    "stop": "高松",
    "tripId": "106_351_20260404",
    "bearing": 0,
    "speed": 0,
    "updateTime": "2026/07/21 19:18:51"
  },
  {
    "company": "wakayama",
    "companyName": "和歌山バス",
    "vehicleNum": "274",
    "lat": 34.22650146484375,
    "lon": 135.16978454589844,
    "route": "市内雑賀崎循環線【33】（新和歌浦行き）",
    "stop": "県庁前",
    "tripId": "106_283_20260404",
    "bearing": 0,
    "speed": 0,
    "updateTime": "2026/07/21 19:19:21"
  },
  {
    "company": "wakayama",
    "companyName": "和歌山バス",
    "vehicleNum": "275",
    "lat": 34.267581939697266,
    "lon": 135.18508911132812,
    "route": "六十谷線【83】（南海和歌山市駅行き）",
    "stop": "近畿大学附属和歌山校前",
    "tripId": "106_581_20260404",
    "bearing": 0,
    "speed": 0,
    "updateTime": "2026/07/21 19:19:36"
  },
  {
    "company": "wakayama",
    "companyName": "和歌山バス",
    "vehicleNum": "279",
    "lat": 34.254581451416016,
    "lon": 135.135498046875,
    "route": "坂田線【75】",
    "stop": "浜代",
    "tripId": "106_418_20260404",
    "bearing": 0,
    "speed": 0,
    "updateTime": "2026/07/21 19:19:44"
  },
  {
    "company": "wakayama",
    "companyName": "和歌山バス",
    "vehicleNum": "321",
    "lat": 34.240196228027344,
    "lon": 135.16839599609375,
    "route": "六十谷線【84】（川永団地行き）",
    "stop": "市駅東",
    "tripId": "106_473_20260404",
    "bearing": 0,
    "speed": 6.388888835906982,
    "updateTime": "2026/07/21 19:19:04"
  },
  {
    "company": "wakayama",
    "companyName": "和歌山バス",
    "vehicleNum": "370",
    "lat": 34.2359733581543,
    "lon": 135.16700744628906,
    "route": "塩屋線【52】（医大病院行き）",
    "stop": "南海和歌山市駅",
    "tripId": "106_958_20260404",
    "bearing": 0,
    "speed": 0,
    "updateTime": "2026/07/21 19:18:54"
  },
  {
    "company": "wakayama",
    "companyName": "和歌山バス",
    "vehicleNum": "373",
    "lat": 34.262001037597656,
    "lon": 135.2024688720703,
    "route": "栄谷線【189】（和歌山大学前駅西口行き）",
    "stop": "鯉川",
    "tripId": "106_552_20260404",
    "bearing": 0,
    "speed": 3.055555582046509,
    "updateTime": "2026/07/21 19:19:22"
  },
  {
    "company": "wakayama",
    "companyName": "和歌山バス",
    "vehicleNum": "454",
    "lat": 34.22458267211914,
    "lon": 135.15988159179688,
    "route": "湊線【60】（南海和歌山市駅行き）",
    "stop": "築地橋",
    "tripId": "106_967_20260404",
    "bearing": 0,
    "speed": 0,
    "updateTime": "2026/07/21 19:19:37"
  },
  {
    "company": "wakayama",
    "companyName": "和歌山バス",
    "vehicleNum": "455",
    "lat": 34.229888916015625,
    "lon": 135.17919921875,
    "route": "紀三井寺線【44】（南海和歌山市駅行き）",
    "stop": "三木町新通",
    "tripId": "106_808_20260404",
    "bearing": 0,
    "speed": 2.777777671813965,
    "updateTime": "2026/07/21 19:19:28"
  },
  {
    "company": "wakayama",
    "companyName": "和歌山バス",
    "vehicleNum": "457",
    "lat": 34.21588897705078,
    "lon": 135.1870880126953,
    "route": "紀三井寺線【44】（医大病院行き）",
    "stop": "新手平",
    "tripId": "106_913_20260404",
    "bearing": 0,
    "speed": 5,
    "updateTime": "2026/07/21 19:18:57"
  },
  {
    "company": "wakayama-naga",
    "companyName": "和歌山バス那賀",
    "vehicleNum": "643",
    "lat": 34.26719284057617,
    "lon": 135.23739624023438,
    "route": "紀伊粉河線【26】（Ｆ．Ｂ．Ｔ（和歌山バス那賀）行き）",
    "stop": "紀伊小学校前",
    "tripId": "2_45_2262_1_62_20260401",
    "bearing": 0,
    "speed": 6.388888835906982,
    "updateTime": "2026/07/21 19:18:37"
  },
  {
    "company": "wakayama-naga",
    "companyName": "和歌山バス那賀",
    "vehicleNum": "706",
    "lat": 34.40219497680664,
    "lon": 135.3448944091797,
    "route": "粉河熊取線【急】（粉河駅前行き）",
    "stop": "青年会場前",
    "tripId": "2_45_2502_1_46_20260401",
    "bearing": 0,
    "speed": 0,
    "updateTime": "2026/07/21 19:18:26"
  },
  {
    "company": "wakayama-naga",
    "companyName": "和歌山バス那賀",
    "vehicleNum": "737",
    "lat": 34.261695861816406,
    "lon": 135.20619201660156,
    "route": "紀伊粉河線【急38】（近畿大学行き）",
    "stop": "六十谷",
    "tripId": "2_45_2381_1_167_20260401",
    "bearing": 0,
    "speed": 2.5,
    "updateTime": "2026/07/21 19:18:27"
  },
  {
    "company": "wakayama-naga",
    "companyName": "和歌山バス那賀",
    "vehicleNum": "760",
    "lat": 34.35239028930664,
    "lon": 135.28128051757812,
    "route": "岩出樽井線【201,202】（岩出駅前行き）",
    "stop": "砂川駅前",
    "tripId": "2_45_2602_1_154_20260401",
    "bearing": 0,
    "speed": 6.666666507720947,
    "updateTime": "2026/07/21 19:18:33"
  },
  {
    "company": "wakayama",
    "companyName": "和歌山バス",
    "vehicleNum": "775",
    "lat": 34.260581970214844,
    "lon": 135.14378356933594,
    "route": "和歌山大学線【172】（東二番丁北行き）",
    "stop": "貴志",
    "tripId": "106_606_20260404",
    "bearing": 0,
    "speed": 2.777777671813965,
    "updateTime": "2026/07/21 19:19:10"
  },
  {
    "company": "wakayama",
    "companyName": "和歌山バス",
    "vehicleNum": "781",
    "lat": 34.20158386230469,
    "lon": 135.17019653320312,
    "route": "和歌山市内線【23】（ＪＲ和歌山駅行き）",
    "stop": "水軒口",
    "tripId": "106_686_20260404",
    "bearing": 0,
    "speed": 0,
    "updateTime": "2026/07/21 19:19:07"
  },
  {
    "company": "wakayama",
    "companyName": "和歌山バス",
    "vehicleNum": "795",
    "lat": 34.27288818359375,
    "lon": 135.1523895263672,
    "route": "和歌山大学線【172】（ＪＲ和歌山駅行き）",
    "stop": "西五番丁",
    "tripId": "106_699_20260404",
    "bearing": 0,
    "speed": 5,
    "updateTime": "2026/07/21 19:19:33"
  },
  {
    "company": "wakayama",
    "companyName": "和歌山バス",
    "vehicleNum": "797",
    "lat": 34.15877914428711,
    "lon": 135.20169067382812,
    "route": "和歌山市内線【121】（ＪＲ和歌山駅行き）",
    "stop": "黒江",
    "tripId": "106_533_20260404",
    "bearing": 0,
    "speed": 7.222222328186035,
    "updateTime": "2026/07/21 19:18:46"
  },
  {
    "company": "wakayama-naga",
    "companyName": "和歌山バス那賀",
    "vehicleNum": "800",
    "lat": 34.28788757324219,
    "lon": 135.3708953857422,
    "route": "粉河熊取線【急】（熊取駅前行き）",
    "stop": "重行",
    "tripId": "2_45_2501_1_89_20260401",
    "bearing": 0,
    "speed": 5.55555534362793,
    "updateTime": "2026/07/21 19:17:51"
  },
  {
    "company": "wakayama",
    "companyName": "和歌山バス",
    "vehicleNum": "820",
    "lat": 34.22997283935547,
    "lon": 135.1761932373047,
    "route": "本町線【0】（ＪＲ和歌山駅行き）",
    "stop": "和歌山城前",
    "tripId": "106_455_20260404",
    "bearing": 0,
    "speed": 3.6111111640930176,
    "updateTime": "2026/07/21 19:19:41"
  },
  {
    "company": "wakayama",
    "companyName": "和歌山バス",
    "vehicleNum": "832",
    "lat": 34.18977737426758,
    "lon": 135.1616973876953,
    "route": "西浜新和歌浦線【35】",
    "stop": "奥天神",
    "tripId": "106_861_20260404",
    "bearing": 0,
    "speed": 7.222222328186035,
    "updateTime": "2026/07/21 19:19:37"
  },
  {
    "company": "wakayama",
    "companyName": "和歌山バス",
    "vehicleNum": "833",
    "lat": 34.237388610839844,
    "lon": 135.1739959716797,
    "route": "塩屋線【53】（医大病院行き）",
    "stop": "本町四丁目",
    "tripId": "106_948_20260404",
    "bearing": 0,
    "speed": 0,
    "updateTime": "2026/07/21 19:19:29"
  },
  {
    "company": "wakayama",
    "companyName": "和歌山バス",
    "vehicleNum": "863",
    "lat": 34.214778900146484,
    "lon": 135.16978454589844,
    "route": "和歌山市内線【117】（南海和歌山市駅行き）",
    "stop": "堀止",
    "tripId": "106_827_20260404",
    "bearing": 0,
    "speed": 4.44444465637207,
    "updateTime": "2026/07/21 19:19:09"
  },
  {
    "company": "wakayama",
    "companyName": "和歌山バス",
    "vehicleNum": "866",
    "lat": 34.231693267822266,
    "lon": 135.16969299316406,
    "route": "和歌山市内線【11】（医大病院行き）",
    "stop": "城北橋",
    "tripId": "106_228_20260404",
    "bearing": 0,
    "speed": 4.166666507720947,
    "updateTime": "2026/07/21 19:19:14"
  },
  {
    "company": "wakayama",
    "companyName": "和歌山バス",
    "vehicleNum": "902",
    "lat": 34.19619369506836,
    "lon": 135.18519592285156,
    "route": "紀三井寺線【42】（南海和歌山市駅行き）",
    "stop": "和田川橋",
    "tripId": "106_367_20260404",
    "bearing": 0,
    "speed": 3.6111111640930176,
    "updateTime": "2026/07/21 19:18:14"
  },
  {
    "company": "wakayama-naga",
    "companyName": "和歌山バス那賀",
    "vehicleNum": "908",
    "lat": 34.276390075683594,
    "lon": 135.32147216796875,
    "route": "紀伊粉河線【26】（近畿大学行き）",
    "stop": "野上野",
    "tripId": "2_45_2261_1_105_20260401",
    "bearing": 0,
    "speed": 1.6666666269302368,
    "updateTime": "2026/07/21 19:18:47"
  },
  {
    "company": "wakayama-naga",
    "companyName": "和歌山バス那賀",
    "vehicleNum": "947",
    "lat": 34.27688980102539,
    "lon": 135.31777954101562,
    "route": "紀伊粉河線【25】（Ｆ．Ｂ．Ｔ（和歌山バス那賀）行き）",
    "stop": "野上野西",
    "tripId": "2_45_2252_1_189_20260401",
    "bearing": 0,
    "speed": 1.9444444179534912,
    "updateTime": "2026/07/21 19:18:30"
  },
  {
    "company": "wakayama-naga",
    "companyName": "和歌山バス那賀",
    "vehicleNum": "948",
    "lat": 34.27199935913086,
    "lon": 135.2711944580078,
    "route": "紀伊粉河線【26】（近畿大学行き）",
    "stop": "池の川",
    "tripId": "2_45_2261_1_123_20260401",
    "bearing": 0,
    "speed": 2.222222328186035,
    "updateTime": "2026/07/21 19:18:31"
  },
  {
    "company": "wakayama",
    "companyName": "和歌山バス",
    "vehicleNum": "951",
    "lat": 34.1636962890625,
    "lon": 135.1876983642578,
    "route": "紀三井寺線【42】（マリーナシティ行き）",
    "stop": "浜の宮",
    "tripId": "106_593_20260404",
    "bearing": 0,
    "speed": 1.9444444179534912,
    "updateTime": "2026/07/21 19:19:27"
  },
  {
    "company": "wakayama-naga",
    "companyName": "和歌山バス那賀",
    "vehicleNum": "962",
    "lat": 34.405277252197266,
    "lon": 135.29539489746094,
    "route": "岩出りんくう線【203】（岩出駅前行き）",
    "stop": "りんくう往来南３番",
    "tripId": "2_45_2632_1_75_20260401",
    "bearing": 0,
    "speed": 2.5,
    "updateTime": "2026/07/21 19:14:04"
  },
  {
    "company": "wakayama",
    "companyName": "和歌山バス",
    "vehicleNum": "978",
    "lat": 34.225276947021484,
    "lon": 135.1699676513672,
    "route": "和歌山市内線【25】（ＪＲ和歌山駅行き）",
    "stop": "県庁前",
    "tripId": "106_648_20260404",
    "bearing": 0,
    "speed": 0,
    "updateTime": "2026/07/21 19:19:11"
  }
]
