[
  {
    "company": "wakayama",
    "companyName": "和歌山バス",
    "vehicleNum": "115",
    "lat": 34.23488998413086,
    "lon": 135.17689514160156,
    "route": "塩屋線【53】（南海和歌山市駅行き）",
    "stop": "ブラクリ丁",
    "tripId": "106_842_20260404",
    "bearing": 0,
    "speed": 0,
    "updateTime": "2026/07/24 18:26:25"
  },
  {
    "company": "wakayama",
    "companyName": "和歌山バス",
    "vehicleNum": "1960",
    "lat": 34.23488998413086,
    "lon": 135.1685791015625,
    "route": "和歌山市内線【117】（南海和歌山市駅行き）",
    "stop": "南海和歌山市駅",
    "tripId": "106_671_20260404",
    "bearing": 0,
    "speed": 6.94444465637207,
    "updateTime": "2026/07/24 18:25:51"
  },
  {
    "company": "wakayama",
    "companyName": "和歌山バス",
    "vehicleNum": "1976",
    "lat": 34.222999572753906,
    "lon": 135.16908264160156,
    "route": "和歌山市内線【23】（ＪＲ和歌山駅行き）",
    "stop": "真砂町",
    "tripId": "106_568_20260404",
    "bearing": 0,
    "speed": 2.222222328186035,
    "updateTime": "2026/07/24 18:26:46"
  },
  {
    "company": "wakayama",
    "companyName": "和歌山バス",
    "vehicleNum": "231",
    "lat": 34.190582275390625,
    "lon": 135.1610870361328,
    "route": "西浜新和歌浦線【35】（南海和歌山市駅行き）",
    "stop": "奥天神",
    "tripId": "106_755_20260404",
    "bearing": 0,
    "speed": 6.666666507720947,
    "updateTime": "2026/07/24 18:26:16"
  },
  {
    "company": "wakayama",
    "companyName": "和歌山バス",
    "vehicleNum": "232",
    "lat": 34.254695892333984,
    "lon": 135.1348876953125,
    "route": "坂田線【75】",
    "stop": "浜代",
    "tripId": "106_956_20260404",
    "bearing": 0,
    "speed": 4.44444465637207,
    "updateTime": "2026/07/24 18:26:28"
  },
  {
    "company": "wakayama",
    "companyName": "和歌山バス",
    "vehicleNum": "233",
    "lat": 34.267887115478516,
    "lon": 135.1479949951172,
    "route": "和歌山大学線【172】（東二番丁北行き）",
    "stop": "藤戸",
    "tripId": "106_876_20260404",
    "bearing": 0,
    "speed": 0,
    "updateTime": "2026/07/24 18:26:23"
  },
  {
    "company": "wakayama",
    "companyName": "和歌山バス",
    "vehicleNum": "235",
    "lat": 34.23158264160156,
    "lon": 135.18600463867188,
    "route": "楠見線【88】（南海和歌山市駅行き）",
    "stop": "新内",
    "tripId": "106_787_20260404",
    "bearing": 0,
    "speed": 1.6666666269302368,
    "updateTime": "2026/07/24 18:26:36"
  },
  {
    "company": "wakayama",
    "companyName": "和歌山バス",
    "vehicleNum": "274",
    "lat": 34.20188903808594,
    "lon": 135.16969299316406,
    "route": "市内雑賀崎循環線【30】（ＪＲ和歌山駅行き）",
    "stop": "水軒口",
    "tripId": "106_282_20260404",
    "bearing": 0,
    "speed": 0,
    "updateTime": "2026/07/24 18:26:09"
  },
  {
    "company": "wakayama",
    "companyName": "和歌山バス",
    "vehicleNum": "279",
    "lat": 34.22538757324219,
    "lon": 135.16989135742188,
    "route": "和歌山市内線【13】（南海和歌山市駅行き）",
    "stop": "県庁前",
    "tripId": "106_417_20260404",
    "bearing": 0,
    "speed": 0,
    "updateTime": "2026/07/24 18:26:31"
  },
  {
    "company": "wakayama",
    "companyName": "和歌山バス",
    "vehicleNum": "321",
    "lat": 34.23158264160156,
    "lon": 135.18618774414062,
    "route": "本町線【0】（南海和歌山市駅行き）",
    "stop": "新内",
    "tripId": "106_472_20260404",
    "bearing": 0,
    "speed": 0,
    "updateTime": "2026/07/24 18:26:25"
  },
  {
    "company": "wakayama",
    "companyName": "和歌山バス",
    "vehicleNum": "322",
    "lat": 34.26119613647461,
    "lon": 135.1844940185547,
    "route": "六十谷線【84】（川永団地行き）",
    "stop": "公民館前",
    "tripId": "106_580_20260404",
    "bearing": 0,
    "speed": 0,
    "updateTime": "2026/07/24 18:26:38"
  },
  {
    "company": "wakayama",
    "companyName": "和歌山バス",
    "vehicleNum": "324",
    "lat": 34.21149826049805,
    "lon": 135.18527221679688,
    "route": "紀三井寺線【42】（南海和歌山市駅行き）",
    "stop": "北中島",
    "tripId": "106_771_20260404",
    "bearing": 0,
    "speed": 3.8888888359069824,
    "updateTime": "2026/07/24 18:26:45"
  },
  {
    "company": "wakayama",
    "companyName": "和歌山バス",
    "vehicleNum": "325",
    "lat": 34.2101936340332,
    "lon": 135.1721954345703,
    "route": "市内雑賀崎循環線【33】（新和歌浦行き）",
    "stop": "高松北",
    "tripId": "106_192_20260404",
    "bearing": 0,
    "speed": 4.166666507720947,
    "updateTime": "2026/07/24 18:25:52"
  },
  {
    "company": "wakayama",
    "companyName": "和歌山バス",
    "vehicleNum": "367",
    "lat": 34.2359733581543,
    "lon": 135.16700744628906,
    "route": "本町線【0】（ＪＲ和歌山駅行き）",
    "stop": "南海和歌山市駅",
    "tripId": "106_226_20260404",
    "bearing": 0,
    "speed": 2.777777671813965,
    "updateTime": "2026/07/24 18:26:38"
  },
  {
    "company": "wakayama",
    "companyName": "和歌山バス",
    "vehicleNum": "368",
    "lat": 34.2359733581543,
    "lon": 135.1671905517578,
    "route": "和歌山市内線【11】（医大病院行き）",
    "stop": "南海和歌山市駅",
    "tripId": "106_685_20260404",
    "bearing": 0,
    "speed": 3.055555582046509,
    "updateTime": "2026/07/24 18:26:36"
  },
  {
    "company": "wakayama",
    "companyName": "和歌山バス",
    "vehicleNum": "370",
    "lat": 34.2597770690918,
    "lon": 135.17689514160156,
    "route": "楠見線【86】（ＪＲ和歌山駅行き）",
    "stop": "楠見小学校前",
    "tripId": "106_892_20260404",
    "bearing": 0,
    "speed": 0,
    "updateTime": "2026/07/24 18:26:14"
  },
  {
    "company": "wakayama",
    "companyName": "和歌山バス",
    "vehicleNum": "371",
    "lat": 34.25658416748047,
    "lon": 135.1523895263672,
    "route": "栄谷線【189】（Ｆ．Ｂ．Ｔ（和歌山バス）行き）",
    "stop": "次郎丸",
    "tripId": "106_551_20260404",
    "bearing": 0,
    "speed": 3.8888888359069824,
    "updateTime": "2026/07/24 18:26:45"
  },
  {
    "company": "wakayama",
    "companyName": "和歌山バス",
    "vehicleNum": "454",
    "lat": 34.253501892089844,
    "lon": 135.14608764648438,
    "route": "和歌山大学線【172】（ＪＲ和歌山駅行き）",
    "stop": "延時",
    "tripId": "106_966_20260404",
    "bearing": 0,
    "speed": 0,
    "updateTime": "2026/07/24 18:26:43"
  },
  {
    "company": "wakayama",
    "companyName": "和歌山バス",
    "vehicleNum": "457",
    "lat": 34.231693267822266,
    "lon": 135.18557739257812,
    "route": "和歌山市内線【24】（ＪＲ和歌山駅行き）",
    "stop": "新内",
    "tripId": "106_911_20260404",
    "bearing": 0,
    "speed": 1.6666666269302368,
    "updateTime": "2026/07/24 18:24:06"
  },
  {
    "company": "wakayama-naga",
    "companyName": "和歌山バス那賀",
    "vehicleNum": "497",
    "lat": 34.37527847290039,
    "lon": 135.35496520996094,
    "route": "粉河熊取線【急】（粉河駅前行き）",
    "stop": "大阪体育大学口",
    "tripId": "2_45_2502_1_177_20260401",
    "bearing": 0,
    "speed": 5.277777671813965,
    "updateTime": "2026/07/24 18:25:20"
  },
  {
    "company": "wakayama-naga",
    "companyName": "和歌山バス那賀",
    "vehicleNum": "583",
    "lat": 34.3609733581543,
    "lon": 135.28219604492188,
    "route": "岩出樽井線【201,202】（岩出駅前行き）",
    "stop": "砂川駅前",
    "tripId": "2_45_2602_1_221_20260401",
    "bearing": 0,
    "speed": 2.222222328186035,
    "updateTime": "2026/07/24 18:25:48"
  },
  {
    "company": "wakayama-naga",
    "companyName": "和歌山バス那賀",
    "vehicleNum": "643",
    "lat": 34.28419494628906,
    "lon": 135.29269409179688,
    "route": "紀伊粉河線【26】（近畿大学行き）",
    "stop": "紀泉台ロータリー",
    "tripId": "2_45_2261_1_61_20260401",
    "bearing": 0,
    "speed": 1.1111111640930176,
    "updateTime": "2026/07/24 18:25:50"
  },
  {
    "company": "wakayama",
    "companyName": "和歌山バス",
    "vehicleNum": "667",
    "lat": 34.207279205322266,
    "lon": 135.1715850830078,
    "route": "和歌山市内線【4】（新和歌浦行き）",
    "stop": "高松",
    "tripId": "106_246_20260404",
    "bearing": 0,
    "speed": 0,
    "updateTime": "2026/07/24 18:26:33"
  },
  {
    "company": "wakayama",
    "companyName": "和歌山バス",
    "vehicleNum": "688",
    "lat": 34.267581939697266,
    "lon": 135.1854705810547,
    "route": "楠見線【187】（南海和歌山市駅行き）",
    "stop": "近畿大学附属和歌山校前",
    "tripId": "106_740_20260404",
    "bearing": 0,
    "speed": 3.055555582046509,
    "updateTime": "2026/07/24 18:18:17"
  },
  {
    "company": "wakayama",
    "companyName": "和歌山バス",
    "vehicleNum": "692",
    "lat": 34.22977828979492,
    "lon": 135.1699676513672,
    "route": "和歌山市内線【121】（海南駅前行き）",
    "stop": "市役所前",
    "tripId": "106_932_20260404",
    "bearing": 0,
    "speed": 0,
    "updateTime": "2026/07/24 18:26:37"
  },
  {
    "company": "wakayama-naga",
    "companyName": "和歌山バス那賀",
    "vehicleNum": "706",
    "lat": 34.3228874206543,
    "lon": 135.37689208984375,
    "route": "粉河熊取線【急】（熊取駅前行き）",
    "stop": "神通",
    "tripId": "2_45_2501_1_45_20260401",
    "bearing": 0,
    "speed": 2.5,
    "updateTime": "2026/07/24 18:25:50"
  },
  {
    "company": "wakayama-naga",
    "companyName": "和歌山バス那賀",
    "vehicleNum": "737",
    "lat": 34.27769470214844,
    "lon": 135.29678344726562,
    "route": "紀伊粉河線【近急】（紀伊駅前行き）",
    "stop": "北大池",
    "tripId": "2_45_2492_1_164_20260401",
    "bearing": 0,
    "speed": 0,
    "updateTime": "2026/07/24 18:25:43"
  },
  {
    "company": "wakayama-naga",
    "companyName": "和歌山バス那賀",
    "vehicleNum": "760",
    "lat": 34.29008483886719,
    "lon": 135.33599853515625,
    "route": "岩出樽井線【201,202】（樽井駅前行き）",
    "stop": "近畿大学",
    "tripId": "2_45_2611_1_153_20260401",
    "bearing": 0,
    "speed": 4.44444465637207,
    "updateTime": "2026/07/24 18:25:39"
  },
  {
    "company": "wakayama",
    "companyName": "和歌山バス",
    "vehicleNum": "770",
    "lat": 34.27577590942383,
    "lon": 135.1475830078125,
    "route": "和歌山大学線【273】（ＪＲ和歌山駅行き）",
    "stop": "和歌山大学前駅",
    "tripId": "106_494_20260404",
    "bearing": 0,
    "speed": 0.2777777910232544,
    "updateTime": "2026/07/24 18:25:26"
  },
  {
    "company": "wakayama",
    "companyName": "和歌山バス",
    "vehicleNum": "781",
    "lat": 34.26069259643555,
    "lon": 135.17999267578125,
    "route": "栄谷線【189】（和歌山大学前駅西口行き）",
    "stop": "大谷東",
    "tripId": "106_511_20260404",
    "bearing": 0,
    "speed": 0.8333333134651184,
    "updateTime": "2026/07/24 18:26:15"
  },
  {
    "company": "wakayama",
    "companyName": "和歌山バス",
    "vehicleNum": "789",
    "lat": 34.22247314453125,
    "lon": 135.15469360351562,
    "route": "湊線【60】（ＪＲ和歌山駅行き）",
    "stop": "築港三丁目",
    "tripId": "106_350_20260404",
    "bearing": 0,
    "speed": 5.55555534362793,
    "updateTime": "2026/07/24 18:26:28"
  },
  {
    "company": "wakayama",
    "companyName": "和歌山バス",
    "vehicleNum": "791",
    "lat": 34.23127746582031,
    "lon": 135.1838836669922,
    "route": "紀三井寺線【44】（南海和歌山市駅行き）",
    "stop": "北の新地",
    "tripId": "106_659_20260404",
    "bearing": 0,
    "speed": 1.6666666269302368,
    "updateTime": "2026/07/24 18:24:54"
  },
  {
    "company": "wakayama",
    "companyName": "和歌山バス",
    "vehicleNum": "795",
    "lat": 34.229888916015625,
    "lon": 135.17088317871094,
    "route": "和歌山大学線【172】（東二番丁北行き）",
    "stop": "市役所前",
    "tripId": "106_698_20260404",
    "bearing": 0,
    "speed": 2.5,
    "updateTime": "2026/07/24 18:26:19"
  },
  {
    "company": "wakayama",
    "companyName": "和歌山バス",
    "vehicleNum": "797",
    "lat": 34.23238754272461,
    "lon": 135.19027709960938,
    "route": "湊線【162】（ＪＲ和歌山駅行き）",
    "stop": "ＪＲ和歌山駅",
    "tripId": "106_646_20260404",
    "bearing": 0,
    "speed": 0,
    "updateTime": "2026/07/24 18:26:27"
  },
  {
    "company": "wakayama-naga",
    "companyName": "和歌山バス那賀",
    "vehicleNum": "800",
    "lat": 34.27119445800781,
    "lon": 135.2701873779297,
    "route": "紀伊粉河線【29】（県立盲学校前行き）",
    "stop": "池の川",
    "tripId": "2_45_2292_1_139_20260401",
    "bearing": 0,
    "speed": 2.5,
    "updateTime": "2026/07/24 18:25:21"
  },
  {
    "company": "wakayama",
    "companyName": "和歌山バス",
    "vehicleNum": "820",
    "lat": 34.21669387817383,
    "lon": 135.15478515625,
    "route": "湊線【60】（南海和歌山市駅行き）",
    "stop": "魁橋",
    "tripId": "106_454_20260404",
    "bearing": 0,
    "speed": 0,
    "updateTime": "2026/07/24 18:26:34"
  },
  {
    "company": "wakayama",
    "companyName": "和歌山バス",
    "vehicleNum": "832",
    "lat": 34.187583923339844,
    "lon": 135.18038940429688,
    "route": "和歌山市内線【11】（南海和歌山市駅行き）",
    "stop": "医大病院",
    "tripId": "106_860_20260404",
    "bearing": 0,
    "speed": 0,
    "updateTime": "2026/07/24 18:26:33"
  },
  {
    "company": "wakayama",
    "companyName": "和歌山バス",
    "vehicleNum": "833",
    "lat": 34.222389221191406,
    "lon": 135.16928100585938,
    "route": "和歌山市内線【13】（和歌浦西行き）",
    "stop": "真砂町",
    "tripId": "106_946_20260404",
    "bearing": 0,
    "speed": 3.055555582046509,
    "updateTime": "2026/07/24 18:26:01"
  },
  {
    "company": "wakayama",
    "companyName": "和歌山バス",
    "vehicleNum": "864",
    "lat": 34.230194091796875,
    "lon": 135.17999267578125,
    "route": "和歌山大学線【172】（ＪＲ和歌山駅行き）",
    "stop": "三木町新通",
    "tripId": "106_398_20260404",
    "bearing": 0,
    "speed": 1.6666666269302368,
    "updateTime": "2026/07/24 18:26:43"
  },
  {
    "company": "wakayama",
    "companyName": "和歌山バス",
    "vehicleNum": "866",
    "lat": 34.229888916015625,
    "lon": 135.17149353027344,
    "route": "和歌山市内線【25】（ＪＲ和歌山駅行き）",
    "stop": "市役所前",
    "tripId": "106_605_20260404",
    "bearing": 0,
    "speed": 3.3333332538604736,
    "updateTime": "2026/07/24 18:26:36"
  },
  {
    "company": "wakayama",
    "companyName": "和歌山バス",
    "vehicleNum": "899",
    "lat": 34.19527816772461,
    "lon": 135.17727661132812,
    "route": "塩屋線【52】（南海和歌山市駅行き）",
    "stop": "和歌浦中央病院前",
    "tripId": "106_382_20260404",
    "bearing": 0,
    "speed": 0.5555555820465088,
    "updateTime": "2026/07/24 18:26:17"
  },
  {
    "company": "wakayama",
    "companyName": "和歌山バス",
    "vehicleNum": "900",
    "lat": 34.230194091796875,
    "lon": 135.17958068847656,
    "route": "和歌山市内線【27】（ＪＲ和歌山駅行き）",
    "stop": "三木町新通",
    "tripId": "106_209_20260404",
    "bearing": 0,
    "speed": 0,
    "updateTime": "2026/07/24 18:26:39"
  },
  {
    "company": "wakayama",
    "companyName": "和歌山バス",
    "vehicleNum": "901",
    "lat": 34.23177719116211,
    "lon": 135.17449951171875,
    "route": "塩屋線【52】（医大病院行き）",
    "stop": "京橋",
    "tripId": "106_433_20260404",
    "bearing": 0,
    "speed": 0,
    "updateTime": "2026/07/24 18:25:48"
  },
  {
    "company": "wakayama",
    "companyName": "和歌山バス",
    "vehicleNum": "902",
    "lat": 34.166194915771484,
    "lon": 135.18739318847656,
    "route": "紀三井寺線【42】（マリーナシティ行き）",
    "stop": "競技場前",
    "tripId": "106_366_20260404",
    "bearing": 0,
    "speed": 3.8888888359069824,
    "updateTime": "2026/07/24 18:25:54"
  },
  {
    "company": "wakayama-naga",
    "companyName": "和歌山バス那賀",
    "vehicleNum": "908",
    "lat": 34.27799987792969,
    "lon": 135.3118896484375,
    "route": "紀伊粉河線【25】（Ｆ．Ｂ．Ｔ（和歌山バス那賀）行き）",
    "stop": "根来東",
    "tripId": "2_45_2252_1_104_20260401",
    "bearing": 0,
    "speed": 1.9444444179534912,
    "updateTime": "2026/07/24 18:25:41"
  },
  {
    "company": "wakayama-naga",
    "companyName": "和歌山バス那賀",
    "vehicleNum": "947",
    "lat": 34.26719284057617,
    "lon": 135.23878479003906,
    "route": "紀伊粉河線【急38】（近畿大学行き）",
    "stop": "紀伊駅前",
    "tripId": "2_45_2381_1_188_20260401",
    "bearing": 0,
    "speed": 5.277777671813965,
    "updateTime": "2026/07/24 18:25:20"
  },
  {
    "company": "wakayama-naga",
    "companyName": "和歌山バス那賀",
    "vehicleNum": "962",
    "lat": 34.36127853393555,
    "lon": 135.28158569335938,
    "route": "岩出りんくう線【203】（りんくうタウン駅前行き）",
    "stop": "砂川駅前",
    "tripId": "2_45_2631_1_74_20260401",
    "bearing": 0,
    "speed": 0.8333333134651184,
    "updateTime": "2026/07/24 18:21:23"
  },
  {
    "company": "wakayama",
    "companyName": "和歌山バス",
    "vehicleNum": "975",
    "lat": 34.21327590942383,
    "lon": 135.18588256835938,
    "route": "紀三井寺線【44】（医大病院行き）",
    "stop": "宮前口",
    "tripId": "106_163_20260404",
    "bearing": 0,
    "speed": 6.111111164093018,
    "updateTime": "2026/07/24 18:26:13"
  },
  {
    "company": "wakayama",
    "companyName": "和歌山バス",
    "vehicleNum": "976",
    "lat": 34.23408508300781,
    "lon": 135.1770782470703,
    "route": "塩屋線【53】（医大病院行き）",
    "stop": "ブラクリ丁",
    "tripId": "106_180_20260404",
    "bearing": 0,
    "speed": 2.5,
    "updateTime": "2026/07/24 18:26:28"
  },
  {
    "company": "wakayama",
    "companyName": "和歌山バス",
    "vehicleNum": "977",
    "lat": 34.159000396728516,
    "lon": 135.19569396972656,
    "route": "和歌山市内線【121】（ＪＲ和歌山駅行き）",
    "stop": "琴の浦",
    "tripId": "106_263_20260404",
    "bearing": 0,
    "speed": 2.5,
    "updateTime": "2026/07/24 18:26:33"
  },
  {
    "company": "wakayama",
    "companyName": "和歌山バス",
    "vehicleNum": "978",
    "lat": 34.185585021972656,
    "lon": 135.18499755859375,
    "route": "和歌山市内線【117】（海南駅前行き）",
    "stop": "紀三井寺住宅前",
    "tripId": "106_531_20260404",
    "bearing": 0,
    "speed": 0,
    "updateTime": "2026/07/24 18:26:19"
  }
]
