[
  {
    "company": "wakayama",
    "companyName": "和歌山バス",
    "vehicleNum": "1976",
    "lat": 34.22997283935547,
    "lon": 135.1759796142578,
    "route": "和歌山市内線【20】（ＪＲ和歌山駅行き）",
    "stop": "和歌山城前",
    "tripId": "106_571_20260404",
    "bearing": 0,
    "speed": 0,
    "updateTime": "2026/07/23 21:16:16"
  },
  {
    "company": "wakayama",
    "companyName": "和歌山バス",
    "vehicleNum": "318",
    "lat": 34.27138900756836,
    "lon": 135.14859008789062,
    "route": "和歌山大学線【172】（ＪＲ和歌山駅行き）",
    "stop": "西三番丁",
    "tripId": "106_609_20260404",
    "bearing": 0,
    "speed": 4.722222328186035,
    "updateTime": "2026/07/23 21:16:44"
  },
  {
    "company": "wakayama",
    "companyName": "和歌山バス",
    "vehicleNum": "321",
    "lat": 34.20738983154297,
    "lon": 135.1715850830078,
    "route": "和歌山市内線【13】（和歌浦西行き）",
    "stop": "高松",
    "tripId": "106_479_20260404",
    "bearing": 0,
    "speed": 3.8888888359069824,
    "updateTime": "2026/07/23 21:16:34"
  },
  {
    "company": "wakayama",
    "companyName": "和歌山バス",
    "vehicleNum": "370",
    "lat": 34.23819351196289,
    "lon": 135.15249633789062,
    "route": "坂田線【75】",
    "stop": "土入橋",
    "tripId": "106_961_20260404",
    "bearing": 0,
    "speed": 4.44444465637207,
    "updateTime": "2026/07/23 21:16:17"
  },
  {
    "company": "wakayama",
    "companyName": "和歌山バス",
    "vehicleNum": "373",
    "lat": 34.23119354248047,
    "lon": 135.1693878173828,
    "route": "和歌山市内線【13】（南海和歌山市駅行き）",
    "stop": "城北橋",
    "tripId": "106_557_20260404",
    "bearing": 0,
    "speed": 5,
    "updateTime": "2026/07/23 21:16:30"
  },
  {
    "company": "wakayama",
    "companyName": "和歌山バス",
    "vehicleNum": "454",
    "lat": 34.18377685546875,
    "lon": 135.18577575683594,
    "route": "和歌山市内線【20】（ＪＲ和歌山駅行き）",
    "stop": "紀三井寺",
    "tripId": "106_970_20260404",
    "bearing": 0,
    "speed": 4.44444465637207,
    "updateTime": "2026/07/23 21:16:41"
  },
  {
    "company": "wakayama-naga",
    "companyName": "和歌山バス那賀",
    "vehicleNum": "497",
    "lat": 34.34049987792969,
    "lon": 135.3735809326172,
    "route": "粉河熊取線【急】（粉河駅前行き）",
    "stop": "犬鳴山",
    "tripId": "2_45_2502_1_179_20260401",
    "bearing": 0,
    "speed": 3.3333332538604736,
    "updateTime": "2026/07/23 21:14:35"
  },
  {
    "company": "wakayama-naga",
    "companyName": "和歌山バス那賀",
    "vehicleNum": "583",
    "lat": 34.323001861572266,
    "lon": 135.306884765625,
    "route": "岩出樽井線【201,202】（樽井駅前行き）",
    "stop": "根来さくらの里",
    "tripId": "2_45_2601_1_224_20260401",
    "bearing": 0,
    "speed": 7.5,
    "updateTime": "2026/07/23 21:16:20"
  },
  {
    "company": "wakayama",
    "companyName": "和歌山バス",
    "vehicleNum": "671",
    "lat": 34.15399932861328,
    "lon": 135.2135009765625,
    "route": "和歌山市内線【6】（和歌浦西行き）",
    "stop": "海南駅前",
    "tripId": "106_498_20260404",
    "bearing": 0,
    "speed": 0,
    "updateTime": "2026/07/23 21:15:53"
  },
  {
    "company": "wakayama-naga",
    "companyName": "和歌山バス那賀",
    "vehicleNum": "737",
    "lat": 34.27808380126953,
    "lon": 135.31158447265625,
    "route": "紀伊粉河線【26】（近畿大学行き）",
    "stop": "根来東",
    "tripId": "2_45_2261_1_169_20260401",
    "bearing": 0,
    "speed": 6.111111164093018,
    "updateTime": "2026/07/23 21:16:28"
  },
  {
    "company": "wakayama-naga",
    "companyName": "和歌山バス那賀",
    "vehicleNum": "760",
    "lat": 34.35438919067383,
    "lon": 135.28070068359375,
    "route": "岩出樽井線【201,202】（岩出駅前行き）",
    "stop": "砂川駅前",
    "tripId": "2_45_2602_1_156_20260401",
    "bearing": 0,
    "speed": 0,
    "updateTime": "2026/07/23 21:16:16"
  },
  {
    "company": "wakayama",
    "companyName": "和歌山バス",
    "vehicleNum": "789",
    "lat": 34.25408172607422,
    "lon": 135.14527893066406,
    "route": "和歌山大学線【172】（東二番丁北行き）",
    "stop": "延時",
    "tripId": "106_689_20260404",
    "bearing": 0,
    "speed": 0,
    "updateTime": "2026/07/23 21:16:34"
  },
  {
    "company": "wakayama",
    "companyName": "和歌山バス",
    "vehicleNum": "791",
    "lat": 34.22977828979492,
    "lon": 135.16989135742188,
    "route": "和歌山市内線【25】（和歌浦西行き）",
    "stop": "市役所前",
    "tripId": "106_663_20260404",
    "bearing": 0,
    "speed": 1.1111111640930176,
    "updateTime": "2026/07/23 21:13:36"
  },
  {
    "company": "wakayama-naga",
    "companyName": "和歌山バス那賀",
    "vehicleNum": "800",
    "lat": 34.26869583129883,
    "lon": 135.24627685546875,
    "route": "紀伊粉河線【24】（粉河駅前行き）",
    "stop": "紀伊駅前",
    "tripId": "2_45_2241_1_144_20260401",
    "bearing": 0,
    "speed": 3.3333332538604736,
    "updateTime": "2026/07/23 21:15:47"
  },
  {
    "company": "wakayama",
    "companyName": "和歌山バス",
    "vehicleNum": "833",
    "lat": 34.22477722167969,
    "lon": 135.16220092773438,
    "route": "湊線【161】（和歌山港駅行き）",
    "stop": "西長町",
    "tripId": "106_951_20260404",
    "bearing": 0,
    "speed": 3.055555582046509,
    "updateTime": "2026/07/23 21:16:06"
  },
  {
    "company": "wakayama-naga",
    "companyName": "和歌山バス那賀",
    "vehicleNum": "948",
    "lat": 34.28138732910156,
    "lon": 135.39768981933594,
    "route": "紀伊粉河線【24】（粉河駅前行き）",
    "stop": "猪の垣",
    "tripId": "2_45_2241_1_125_20260401",
    "bearing": 0,
    "speed": 8.333333015441895,
    "updateTime": "2026/07/23 21:16:32"
  },
  {
    "company": "wakayama",
    "companyName": "和歌山バス",
    "vehicleNum": "951",
    "lat": 34.185081481933594,
    "lon": 135.18557739257812,
    "route": "和歌山市内線【17】（海南駅前行き）",
    "stop": "紀三井寺",
    "tripId": "106_595_20260404",
    "bearing": 0,
    "speed": 0,
    "updateTime": "2026/07/23 21:16:14"
  }
]
